http_tunnel/cli.py
http_tunnel/client.py
http_tunnel/common.py
http_tunnel/crypto.py
http_tunnel/server.py
http_tunnel-0.6.65.dist-info/LICENSE
http_tunnel-0.6.65.dist-info/METADATA
http_tunnel-0.6.65.dist-info/WHEEL
http_tunnel-0.6.65.dist-info/entry_points.txt
http_tunnel-0.6.65.dist-info/top_level.txt
http_tunnel-0.6.65.dist-info/RECORD
