Metadata-Version: 2.1
Name: http-tunnel
Version: 0.6.65
Summary: HTTP tunneling tool.
Home-page: https://github.com/yxc890123/http-tunnel
Author: yxc890123
License: Apache 2.0
Classifier: License :: OSI Approved :: Apache Software License
Classifier: Operating System :: Microsoft :: Windows
Classifier: Operating System :: POSIX :: Linux
Classifier: Programming Language :: Python :: 3
Requires-Python: >=3.8
License-File: LICENSE
Requires-Dist: requests[socks]
Requires-Dist: fastapi-slim
Requires-Dist: uvicorn
Requires-Dist: websockets
Requires-Dist: cryptography
